domaintrails/__init__.py
domaintrails/portal.py
domaintrails/core/__init__.py
domaintrails/core/resources.py
domaintrails/core/parser/__init__.py
domaintrails/core/parser/html_parser.py
domaintrails/core/recon/__init__.py
domaintrails/core/recon/dns_history.py
domaintrails/core/recon/dnslg.py
domaintrails/core/recon/domain_available.py
domain_trails-1.0.0.dist-info/LICENSE
domain_trails-1.0.0.dist-info/METADATA
domain_trails-1.0.0.dist-info/WHEEL
domain_trails-1.0.0.dist-info/entry_points.txt
domain_trails-1.0.0.dist-info/top_level.txt
domain_trails-1.0.0.dist-info/RECORD
