Metadata-Version: 2.1
Name: domain-trails
Version: 1.0.0
Summary: Domain trails is open source intelligence gathering tool. This tool collect information related to domain. 
Home-page: https://github.com/iAbdullahMughal/domain-trails
Author: Muhammad Abdullah
Author-email: iamabdullahmughal@gmail.com
License: UNKNOWN
Project-URL: Bug Tracker, https://github.com/iAbdullahMughal/domain-trails/issues
Platform: UNKNOWN
Classifier: Programming Language :: Python :: 3.6
Classifier: License :: OSI Approved :: MIT License
Classifier: Operating System :: OS Independent
Requires-Python: >=3.6
License-File: LICENSE
